qwer_python/__init__.py
qwer_python/__main__.py
qwer_python/adb_handler.py
qwer_python/config_manager.py
qwer_python/csv_handler.py
qwer_python/feature_handler.py
qwer_python/game_data_getter.py
qwer_python/helper.py
qwer_python/item.py
qwer_python/locale_handler.py
qwer_python/managed_item.py
qwer_python/parse_save.py
qwer_python/patcher.py
qwer_python/root_handler.py
qwer_python/serialise_save.py
qwer_python/server_handler.py
qwer_python/tracker.py
qwer_python/updater.py
qwer_python/user_input_handler.py
qwer_python/edits/__init__.py
qwer_python/edits/basic/__init__.py
qwer_python/edits/basic/basic_items.py
qwer_python/edits/basic/catfruit.py
qwer_python/edits/basic/catseyes.py
qwer_python/edits/basic/ototo_base_mats.py
qwer_python/edits/basic/talent_orbs.py
qwer_python/edits/basic/talent_orbs_new.py
qwer_python/edits/cats/__init__.py
qwer_python/edits/cats/cat_helper.py
qwer_python/edits/cats/cat_id_selector.py
qwer_python/edits/cats/chara_drop.py
qwer_python/edits/cats/clear_cat_guide.py
qwer_python/edits/cats/evolve_cats.py
qwer_python/edits/cats/get_remove_cats.py
qwer_python/edits/cats/talents.py
qwer_python/edits/cats/upgrade_blue.py
qwer_python/edits/cats/upgrade_cats.py
qwer_python/edits/gamototo/__init__.py
qwer_python/edits/gamototo/fix_gamatoto.py
qwer_python/edits/gamototo/gamatoto_xp.py
qwer_python/edits/gamototo/helpers.py
qwer_python/edits/gamototo/ototo_cat_cannon.py
qwer_python/edits/levels/__init__.py
qwer_python/edits/levels/aku.py
qwer_python/edits/levels/allow_filibuster_clearing.py
qwer_python/edits/levels/behemoth_culling.py
qwer_python/edits/levels/clear_tutorial.py
qwer_python/edits/levels/enigma_stages.py
qwer_python/edits/levels/event_stages.py
qwer_python/edits/levels/gauntlet.py
qwer_python/edits/levels/itf_timed_scores.py
qwer_python/edits/levels/legend_quest.py
qwer_python/edits/levels/main_story.py
qwer_python/edits/levels/outbreaks.py
qwer_python/edits/levels/story_level_id_selector.py
qwer_python/edits/levels/towers.py
qwer_python-0.0.2.dist-info/METADATA
qwer_python-0.0.2.dist-info/WHEEL
qwer_python-0.0.2.dist-info/top_level.txt
qwer_python-0.0.2.dist-info/RECORD
